pyo3Tree-0.1.2.dist-info/METADATA
pyo3Tree-0.1.2.dist-info/WHEEL
pyo3Tree/__init__.py
pyo3Tree/pyo3Tree.pyd
pyo3Tree-0.1.2.dist-info/RECORD
