Metadata-Version: 2.1
Name: pyo3Tree
Version: 0.1.2
Classifier: Programming Language :: Python
Classifier: Programming Language :: Rust
Classifier: Development Status :: 4 - Beta
Classifier: Intended Audience :: Developers
Classifier: License :: OSI Approved :: MIT License
Classifier: Operating System :: OS Independent
Summary: tree module package
Home-Page: 
Author: GlenAMacdonald
Author-email: macdonald.glen.a@gmail.com
License: Apache-2.0
Requires-Python: >=3.8
Project-URL: URL, https://github.com/GlenAMacdonald/pyo3Tree
